{
  "$schema": "https://dev.office.com/json-schemas/spfx-build/package-solution.schema.json",
  "solution": {
    "name": "custom-footer-client-side-solution",
    "id": "7d0fbda4-ec2f-4618-8982-a82c0f7ff7e5",
    "version": "1.0.4.6",
    "includeClientSideAssets": true,
    "webApiPermissionRequests": [
      {
        "resource": "Microsoft Graph",
        "scope": "Mail.ReadWrite"
      }
    ],
    "features": [
      {
        "title": "Application Extension - Deployment of custom action.",
        "description": "Deploys a custom action with ClientSideComponentId association",
        "id": "11797818-6013-49a2-a786-632265381c6e",
        "version": "1.0.0.0",
        "assets": {
          "elementManifests": [
            "elements.xml"
          ]
        }
      }
    ]
  },
  "paths": {
    "zippedPackage": "solution/custom-footer.sppkg"
  }
}
